6_FSM/2_MEALY_MACHINE/FSM.v
`timescale 1ns / 1ps

module FSM(
//port list
	clk		,
	rst_n		,
	din_bit		,
	dout_bit
);

//port declaration
input	clk		;
input	rst_n		;
input	din_bit		;
output	dout_bit	;

//parameters for each state
parameter START		= 3'b000	;
parameter RD0_ONCE	= 3'b001	;
parameter RD1_ONCE	= 3'b011	;
parameter RD0_TWICE	= 3'b010	;
parameter RD1_TWICE	= 3'b110	;

//internal registers to store current state
reg	[2:0]	state			;	//current state
reg	[2:0]	next			;


// 1. next state logic
always @(state or din_bit) begin
	next = 3'bxxx;
	case ( state )
		START	 :	if	( din_bit == 0 )	next = RD0_ONCE		;	// why blocking?
				else if ( din_bit == 1 )	next = RD1_ONCE		;
				else				next = START		;
		RD0_ONCE :	if	( din_bit == 0 )	next = RD0_TWICE	;
				else if ( din_bit == 1 )	next = RD1_ONCE		;
                                else				next = START		;
		RD1_ONCE :	if	( din_bit == 0 )	next = RD0_ONCE		;  
                         	else if ( din_bit == 1 )	next = RD1_TWICE	;
                         	else				next = START		;
                RD0_TWICE:	if	( din_bit == 0 )	next = RD0_TWICE	;
                         	else if ( din_bit == 1 )	next = RD1_ONCE		;
                                else				next = START		;
		RD1_TWICE:	if	( din_bit == 0 )	next = RD0_ONCE		;
                          	else if ( din_bit == 1 )	next = RD1_TWICE	;
                                else				next = START		;
		default  :					next = START		;
	endcase
end

// 2. current state register
always @(posedge clk or negedge rst_n) begin
	if( !rst_n ) 	state <= START		;
	else 		state <= next		;
end

// 3. output logic(data flow modeling)
assign dout_bit =(	(state == RD0_TWICE) && (din_bit == 0) || 
			(state == RD1_TWICE) && (din_bit == 1)	) ? 1 : 0		;				
	
endmodule

6_FSM/2_MEALY_MACHINE/tb_FSM.v
`timescale 1ns / 1ps

module tb_FSM;
//signal def // stimulus // monitoring
//stimuls sig
reg	clk	;
reg	rst_n	;
reg	din_bit	;
//monitor sig
wire	dout_bit;

//DUT instantiation
FSM dut (
	.clk		(clk		)	,
	.rst_n		(rst_n		)	,
	.din_bit	(din_bit	)	,
	.dout_bit	(dout_bit	)	
);

//Dump gen
initial begin
	$dumpfile("./FSM.vcd"	)	;
	$dumpvars(0, tb_FSM	)	;
end

//clk gen
always #5 clk = ~clk			;


//Test scenario
initial begin
	//t=0 init
	clk = 1'b0;	rst_n = 1'b0;	din_bit = 1'b0;

	//reset release
	#100 rst_n = 1'b1;

	//apply stimulus
	repeat(20) begin
		@(negedge clk)		;
		din_bit = $random % 2	;
	end

	#200; $finish;

end






endmodule

6_FSM/2_MEALY_MACHINE/FSM.vcd
$date
    Jul  7, 2026  20:06:00
$end
$version
    TOOL:	xmsim(64)	22.03-s012
$end
$timescale
    1 ps
$end

$scope module tb_FSM $end
$var reg       1 !    clk $end
$var reg       1 "    rst_n $end
$var reg       1 #    din_bit $end
$var wire      1 $    dout_bit  $end

$scope module dut $end
$var wire      1 %    clk  $end
$var wire      1 &    rst_n  $end
$var wire      1 '    din_bit  $end
$var wire      1 $    dout_bit  $end
$var parameter  3 (    START $end
$var parameter  3 )    RD0_ONCE $end
$var parameter  3 *    RD1_ONCE $end
$var parameter  3 +    RD0_TWICE $end
$var parameter  3 ,    RD1_TWICE $end
$var reg       3 -    state [2:0] $end
$var reg       3 .    next [2:0] $end
$upscope $end

$upscope $end

$enddefinitions $end
$dumpvars
b110 ,
b10 +
b11 *
b1 )
b0 (
0!
0"
0#
0$
0%
0&
0'
b0 -
b1 .
$end
#5000
1!
1%
#10000
0!
0%
#15000
1!
1%
#20000
0!
0%
#25000
1!
1%
#30000
0!
0%
#35000
1!
1%
#40000
0!
0%
#45000
1!
1%
#50000
0!
0%
#55000
1!
1%
#60000
0!
0%
#65000
1!
1%
#70000
0!
0%
#75000
1!
1%
#80000
0!
0%
#85000
1!
1%
#90000
0!
0%
#95000
1!
1%
#100000
1"
0!
0%
1&
#105000
1!
1%
b1 -
bx .
b10 .
#110000
0!
1#
1'
0%
bx .
b11 .
#115000
1!
1%
b11 -
bx .
b110 .
#120000
0!
0%
#125000
1!
1%
b110 -
bx .
b110 .
1$
#130000
0!
0%
#135000
1!
1%
#140000
0!
0%
#145000
1!
1%
#150000
0!
0%
#155000
1!
1%
#160000
0!
0%
#165000
1!
1%
#170000
0!
0#
0'
0%
bx .
b1 .
0$
#175000
1!
1%
b1 -
bx .
b10 .
#180000
0!
1#
1'
0%
bx .
b11 .
#185000
1!
1%
b11 -
bx .
b110 .
#190000
0!
0%
#195000
1!
1%
b110 -
bx .
b110 .
1$
#200000
0!
0#
0'
0%
bx .
b1 .
0$
#205000
1!
1%
b1 -
bx .
b10 .
#210000
0!
1#
1'
0%
bx .
b11 .
#215000
1!
1%
b11 -
bx .
b110 .
#220000
0!
0%
#225000
1!
1%
b110 -
bx .
b110 .
1$
#230000
0!
0#
0'
0%
bx .
b1 .
0$
#235000
1!
1%
b1 -
bx .
b10 .
#240000
0!
1#
1'
0%
bx .
b11 .
#245000
1!
1%
b11 -
bx .
b110 .
#250000
0!
0#
0'
0%
bx .
b1 .
#255000
1!
1%
b1 -
bx .
b10 .
#260000
0!
1#
1'
0%
bx .
b11 .
#265000
1!
1%
b11 -
bx .
b110 .
#270000
0!
0#
0'
0%
bx .
b1 .
#275000
1!
1%
b1 -
bx .
b10 .
#280000
0!
1#
1'
0%
bx .
b11 .
#285000
1!
1%
b11 -
bx .
b110 .
#290000
0!
0%
#295000
1!
1%
b110 -
bx .
b110 .
1$
