6_FSM/1_MOORE_MACHINE/1_assign_output/FSM1.v
`timescale 1ns / 1ps

module FSM1(
	//port list
	clk	,
	rst_n	,
	go	,
	ws	,
	rd	,
	ds
);
//port declaration
input	clk	;
input	rst_n	;
input 	go	;
input	ws	;
output	rd	;
output	ds	;

//parameters for each state
parameter IDLE	= 2'b00;
parameter READ	= 2'b01;
parameter DLY	= 2'b11;
parameter DONE	= 2'b10;

//internal register to store current state
reg	[1:0]	state; //curret state
reg	[1:0]	next;

// 1. next state logic
always @(posedge clk or negedge rst_n) begin
	next = 2'bx; // initial state		why x?
	case ( state )	// read current state
		IDLE :	if( go )		next = READ	;
			else			next = IDLE	;
		READ :				next = DLY	;
		DLY  :	if( !ws )		next = DONE	;
			else			next = READ	;
		DONE :				next = IDLE	;
	endcase
end

// 2. current state register
always @(posedge clk or negedge rst_n) begin
	if(!rst_n) 	state <= IDLE	;
	else 		state <= next	;	
end

// 3. output logic (data flow modeling) : Moore Machine
assign rd = (state == READ) || (state == DLY)	;
assign ds = (state == DONE)			;

endmodule

6_FSM/1_MOORE_MACHINE/1_assign_output/tb_FSM1.v
`timescale 1ns / 1ps

module tb_FSM1;
//local parameters
//stimulus sig
reg clk		;
reg rst_n	;
reg go		;
reg ws		;
//monitor sig
wire rd		;
wire ds		;
//DUT instantiation (with designated parameters)
FSM1 DUT (
	.clk	(clk	)	,
	.rst_n	(rst_n	)	,
	.go	(go	)	,
	.ws	(ws	)	,
	.rd	(rd	)	,
	.ds	(ds	)	
);
//dumpfile gen
initial begin
	$dumpfile("./FSM1.vcd")	;
	$dumpvars(0, tb_FSM1)	;
end
//clk gen
always #5 clk = ~clk;
//Test scenario //init //apply stimulus
initial begin
	//t=0, init
	clk = 1'b0;	rst_n = 1'b0;
	go = 1'b0;	ws = 1'b0;

	#100 rst_n = 1'b1; // rst off(system on)

	#100 go = 1'b1; ws = 1'b1;
	#100 ws = 1'b0;
	#100 rst_n = 1'b0;
	#100; $finish;
end

endmodule

6_FSM/1_MOORE_MACHINE/1_assign_output/FSM1.vcd
$date
    Jul  7, 2026  00:57:49
$end
$version
    TOOL:	xmsim(64)	22.03-s012
$end
$timescale
    1 ps
$end

$scope module tb_FSM1 $end
$var reg       1 !    clk $end
$var reg       1 "    rst_n $end
$var reg       1 #    go $end
$var reg       1 $    ws $end
$var wire      1 %    rd  $end
$var wire      1 &    ds  $end

$scope module DUT $end
$var wire      1 '    clk  $end
$var wire      1 (    rst_n  $end
$var wire      1 )    go  $end
$var wire      1 *    ws  $end
$var wire      1 %    rd  $end
$var wire      1 &    ds  $end
$var parameter  2 +    IDLE $end
$var parameter  2 ,    READ $end
$var parameter  2 -    DLY $end
$var parameter  2 .    DONE $end
$var reg       2 /    state [1:0] $end
$var reg       2 0    next [1:0] $end
$upscope $end

$upscope $end

$enddefinitions $end
$dumpvars
b10 .
b11 -
b1 ,
b0 +
0!
0"
0#
0$
0%
0&
0'
0(
0)
0*
b0 /
bx 0
$end
#5000
1!
1'
b0 0
#10000
0!
0'
#15000
1!
1'
bx 0
b0 0
#20000
0!
0'
#25000
1!
1'
bx 0
b0 0
#30000
0!
0'
#35000
1!
1'
bx 0
b0 0
#40000
0!
0'
#45000
1!
1'
bx 0
b0 0
#50000
0!
0'
#55000
1!
1'
bx 0
b0 0
#60000
0!
0'
#65000
1!
1'
bx 0
b0 0
#70000
0!
0'
#75000
1!
1'
bx 0
b0 0
#80000
0!
0'
#85000
1!
1'
bx 0
b0 0
#90000
0!
0'
#95000
1!
1'
bx 0
b0 0
#100000
1"
0!
0'
1(
#105000
1!
1'
bx 0
b0 0
#110000
0!
0'
#115000
1!
1'
bx 0
b0 0
#120000
0!
0'
#125000
1!
1'
bx 0
b0 0
#130000
0!
0'
#135000
1!
1'
bx 0
b0 0
#140000
0!
0'
#145000
1!
1'
bx 0
b0 0
#150000
0!
0'
#155000
1!
1'
bx 0
b0 0
#160000
0!
0'
#165000
1!
1'
bx 0
b0 0
#170000
0!
0'
#175000
1!
1'
bx 0
b0 0
#180000
0!
0'
#185000
1!
1'
bx 0
b0 0
#190000
0!
0'
#195000
1!
1'
bx 0
b0 0
#200000
1#
1$
0!
0'
1*
1)
#205000
1!
1'
bx 0
b1 0
b1 /
1%
#210000
0!
0'
#215000
1!
1'
bx 0
b11 0
b11 /
#220000
0!
0'
#225000
1!
1'
bx 0
b1 0
b1 /
#230000
0!
0'
#235000
1!
1'
bx 0
b11 0
b11 /
#240000
0!
0'
#245000
1!
1'
bx 0
b1 0
b1 /
#250000
0!
0'
#255000
1!
1'
bx 0
b11 0
b11 /
#260000
0!
0'
#265000
1!
1'
bx 0
b1 0
b1 /
#270000
0!
0'
#275000
1!
1'
bx 0
b11 0
b11 /
#280000
0!
0'
#285000
1!
1'
bx 0
b1 0
b1 /
#290000
0!
0'
#295000
1!
1'
bx 0
b11 0
b11 /
#300000
0$
0!
0'
0*
#305000
1!
1'
bx 0
b10 0
b10 /
1&
0%
#310000
0!
0'
#315000
1!
1'
bx 0
b0 0
b0 /
0&
#320000
0!
0'
#325000
1!
1'
bx 0
b1 0
b1 /
1%
#330000
0!
0'
#335000
1!
1'
bx 0
b11 0
b11 /
#340000
0!
0'
#345000
1!
1'
bx 0
b10 0
b10 /
1&
0%
#350000
0!
0'
#355000
1!
1'
bx 0
b0 0
b0 /
0&
#360000
0!
0'
#365000
1!
1'
bx 0
b1 0
b1 /
1%
#370000
0!
0'
#375000
1!
1'
bx 0
b11 0
b11 /
#380000
0!
0'
#385000
1!
1'
bx 0
b10 0
b10 /
1&
0%
#390000
0!
0'
#395000
1!
1'
bx 0
b0 0
b0 /
0&
#400000
0"
0!
0'
0(
bx 0
b1 0
#405000
1!
1'
bx 0
b1 0
#410000
0!
0'
#415000
1!
1'
bx 0
b1 0
#420000
0!
0'
#425000
1!
1'
bx 0
b1 0
#430000
0!
0'
#435000
1!
1'
bx 0
b1 0
#440000
0!
0'
#445000
1!
1'
bx 0
b1 0
#450000
0!
0'
#455000
1!
1'
bx 0
b1 0
#460000
0!
0'
#465000
1!
1'
bx 0
b1 0
#470000
0!
0'
#475000
1!
1'
bx 0
b1 0
#480000
0!
0'
#485000
1!
1'
bx 0
b1 0
#490000
0!
0'
#495000
1!
1'
bx 0
b1 0
