6_FSM/1_MOORE_MACHINE/3_reg_output/FSM3.v
`timescale 1ns / 1ps

module FSM3(
	//port list
	clk		, 
	rst_n		, 
	go		, 
	ws		, 
	rd		, 
	ds
);
//port declaration
input 	clk			;
input 	rst_n			;
input 	go			;
input 	ws			;
output 	rd			;
output 	ds			;

//parameters for each state
parameter IDLE 	= 2'b00						;
parameter READ 	= 2'b01						;
parameter DLY 	= 2'b11						;
parameter DONE 	= 2'b10						;

//internal registers to store current state
reg	[1:0]	state	;
reg	[1:0]	next	;

// 1. next state logic
always @(state, go, ws) begin
	next = 2'bx;
	case ( state )
		IDLE : if ( go )	 	next = READ		;
		       else	 	 	next = IDLE		;
		READ : 			 	next = DLY		;
		DLY  : if ( !ws ) 		next = DONE		;
		       else 			next = READ		;
		DONE : 				next = IDLE		;
	endcase
end

// 2. curret state register
always @(posedge clk or negedge rst_n) begin
	if( !rst_n ) 	state <= IDLE	;
	else		state <= next	;
end

// 3. output logic (behavioral modeling)
reg rd;
reg ds;
always @(posedge clk or negedge rst_n) begin
	if( !rst_n ) begin
		rd <= 1'b0			;
		ds <= 1'b0			;
	end
	else begin
		case ( next )
			READ : rd <= 1'b1	;
			DLY  : rd <= 1'b1	;
			DONE : ds <= 1'b1	;
		endcase
	end
end


endmodule

6_FSM/1_MOORE_MACHINE/3_reg_output/tb_FSM3.v
`timescale 1ns / 1ps

module tb_FSM3;
//localparams
//stimulus sig
reg	clk	;	
reg	rst_n	;
reg	go	;
reg	ws	;
//monitor sig
wire	rd	;
wire	ds	;
//DUT instantiation
FSM3 dut (
	.clk	(clk	)	,
	.rst_n	(rst_n	)	,
	.go	(go	)	,
	.ws	(ws	)	,
	.rd	(rd	)	,
	.ds	(ds	)	
);
//Dump gen
initial begin
	$dumpfile("./FSM3.vcd"	)	;
	$dumpvars(0, tb_FSM3	)	;
end
//clk gen
always #5 clk = ~clk	;
//apply stimulus //init
initial begin
	//t=0, init
	clk = 1'b0; rst_n = 1'b0; // reset on
	go =1'b0; ws = 1'b0;

	#100 rst_n = 1'b1; // rst off
	
	//apply stimulus
	#100 go = 1'b1;	ws = 1'b1;
	#100 ws = 1'b0;
	#100 rst_n = 1'b0;
	#100; $finish;
end

endmodule

6_FSM/1_MOORE_MACHINE/3_reg_output/FSM3.vcd
$date
    Jul  7, 2026  02:22:59
$end
$version
    TOOL:	xmsim(64)	22.03-s012
$end
$timescale
    1 ps
$end

$scope module tb_FSM3 $end
$var reg       1 !    clk $end
$var reg       1 "    rst_n $end
$var reg       1 #    go $end
$var reg       1 $    ws $end
$var wire      1 %    rd  $end
$var wire      1 &    ds  $end

$scope module dut $end
$var wire      1 '    clk  $end
$var wire      1 (    rst_n  $end
$var wire      1 )    go  $end
$var wire      1 *    ws  $end
$var reg       1 +    rd $end
$var reg       1 ,    ds $end
$var parameter  2 -    IDLE $end
$var parameter  2 .    READ $end
$var parameter  2 /    DLY $end
$var parameter  2 0    DONE $end
$var reg       2 1    state [1:0] $end
$var reg       2 2    next [1:0] $end
$upscope $end

$upscope $end

$enddefinitions $end
$dumpvars
b10 0
b11 /
b1 .
b0 -
0!
0"
0#
0$
0%
0&
0'
0(
0)
0*
0+
0,
b0 1
b0 2
$end
#5000
1!
1'
#10000
0!
0'
#15000
1!
1'
#20000
0!
0'
#25000
1!
1'
#30000
0!
0'
#35000
1!
1'
#40000
0!
0'
#45000
1!
1'
#50000
0!
0'
#55000
1!
1'
#60000
0!
0'
#65000
1!
1'
#70000
0!
0'
#75000
1!
1'
#80000
0!
0'
#85000
1!
1'
#90000
0!
0'
#95000
1!
1'
#100000
1"
0!
0'
1(
#105000
1!
1'
#110000
0!
0'
#115000
1!
1'
#120000
0!
0'
#125000
1!
1'
#130000
0!
0'
#135000
1!
1'
#140000
0!
0'
#145000
1!
1'
#150000
0!
0'
#155000
1!
1'
#160000
0!
0'
#165000
1!
1'
#170000
0!
0'
#175000
1!
1'
#180000
0!
0'
#185000
1!
1'
#190000
0!
0'
#195000
1!
1'
#200000
1#
1$
0!
0'
1*
1)
bx 2
b1 2
#205000
1!
1'
1+
b1 1
bx 2
b11 2
1%
#210000
0!
0'
#215000
1!
1'
b11 1
bx 2
b1 2
#220000
0!
0'
#225000
1!
1'
b1 1
bx 2
b11 2
#230000
0!
0'
#235000
1!
1'
b11 1
bx 2
b1 2
#240000
0!
0'
#245000
1!
1'
b1 1
bx 2
b11 2
#250000
0!
0'
#255000
1!
1'
b11 1
bx 2
b1 2
#260000
0!
0'
#265000
1!
1'
b1 1
bx 2
b11 2
#270000
0!
0'
#275000
1!
1'
b11 1
bx 2
b1 2
#280000
0!
0'
#285000
1!
1'
b1 1
bx 2
b11 2
#290000
0!
0'
#295000
1!
1'
b11 1
bx 2
b1 2
#300000
0$
0!
0'
0*
bx 2
b10 2
#305000
1!
1'
1,
b10 1
bx 2
b0 2
1&
#310000
0!
0'
#315000
1!
1'
b0 1
bx 2
b1 2
#320000
0!
0'
#325000
1!
1'
b1 1
bx 2
b11 2
#330000
0!
0'
#335000
1!
1'
b11 1
bx 2
b10 2
#340000
0!
0'
#345000
1!
1'
b10 1
bx 2
b0 2
#350000
0!
0'
#355000
1!
1'
b0 1
bx 2
b1 2
#360000
0!
0'
#365000
1!
1'
b1 1
bx 2
b11 2
#370000
0!
0'
#375000
1!
1'
b11 1
bx 2
b10 2
#380000
0!
0'
#385000
1!
1'
b10 1
bx 2
b0 2
#390000
0!
0'
#395000
1!
1'
b0 1
bx 2
b1 2
#400000
0"
0!
0'
0(
0+
0,
0&
0%
